awshelp.py
awshelp-1.0.0.dist-info/LICENSE
awshelp-1.0.0.dist-info/METADATA
awshelp-1.0.0.dist-info/WHEEL
awshelp-1.0.0.dist-info/entry_points.txt
awshelp-1.0.0.dist-info/top_level.txt
awshelp-1.0.0.dist-info/RECORD
